Metadata-Version: 2.1
Name: mission-naming
Version: 1.0.0
Summary: A library to generate random mission names
Home-page: https://github.com/rphlo/mission_codenames
Author: Raphael Stefanini
Author-email: raphael@rphlo.com
License: UNKNOWN
Download-URL: https://github.com/rphlo/mission_codenames/tarball/1.0.0
Keywords: random,naming,name,mission
Platform: UNKNOWN
Classifier: Operating System :: OS Independent
Classifier: Programming Language :: Python
Classifier: Programming Language :: Python :: 2
Classifier: Programming Language :: Python :: 3
